drf_nest/__init__.py
drf_nest/admin.py
drf_nest/api.py
drf_nest/batch_migrate.py
drf_nest/fields.py
drf_nest/pagination.py
drf_nest/permissions.py
drf_nest/routers.py
drf_nest/serializer_fields.py
drf_nest/serializers.py
drf_nest/signals.py
drf_nest/templates/admin/textinput_filter.html
drf_nest-0.1a5.dist-info/LICENSE
drf_nest-0.1a5.dist-info/METADATA
drf_nest-0.1a5.dist-info/WHEEL
drf_nest-0.1a5.dist-info/top_level.txt
drf_nest-0.1a5.dist-info/RECORD
