Metadata-Version: 2.1
Name: drf-nest
Version: 0.1a5
Summary: Django rest framework extension to handle writable nested fields
Home-page: https://github.com/Semprini/drf-nest
Author: Semprini
Author-email: dont@contact.me
License: UNKNOWN
Platform: UNKNOWN
Classifier: Programming Language :: Python :: 3
Classifier: License :: OSI Approved :: GNU General Public License (GPL)
Classifier: Operating System :: OS Independent
Requires-Python: >=3.7
Requires-Dist: django (>=3)
Requires-Dist: djangorestframework (>=3.7.7)
Requires-Dist: django-filter (>=0.15.3)
